xethhung12_minio_download_file/__init__.py
xethhung12_minio_download_file/__main__.py
xethhung12_minio_download_file/download_file.py
xethhung12_minio_download_file-0.0.14.dist-info/METADATA
xethhung12_minio_download_file-0.0.14.dist-info/WHEEL
xethhung12_minio_download_file-0.0.14.dist-info/licenses/LICENSE
xethhung12_minio_download_file-0.0.14.dist-info/RECORD
