Metadata-Version: 2.1
Name: xethhung12_minio_download_file
Version: 0.0.14
Summary: A small program downloading file to minio repo
Project-URL: Homepage, https://github.com/xh-dev/xethhung12_minio_download_file
Project-URL: Bug Tracker, https://github.com/xh-dev/xethhung12_minio_download_file/issues
Author-email: Xeth Hung <admin@xethh.me>
License-File: LICENSE
Classifier: License :: OSI Approved :: MIT License
Classifier: Operating System :: OS Independent
Classifier: Programming Language :: Python :: 3
Requires-Python: >=3.7
Requires-Dist: xethhung12-minio-common>=0.0.2
